getproxy/__init__.py
getproxy/cli.py
getproxy/getproxy.py
getproxy/utils.py
getproxy/data/GeoLite2-Country.mmdb
getproxy/plugin/__init__.py
getproxy/plugin/cnproxy.py
getproxy/plugin/coolproxy.py
getproxy/plugin/freeproxylist.py
getproxy/plugin/ip181.py
getproxy/plugin/proxylist.py
getproxy/plugin/txt.py
getproxy-0.2.3.dist-info/DESCRIPTION.rst
getproxy-0.2.3.dist-info/METADATA
getproxy-0.2.3.dist-info/RECORD
getproxy-0.2.3.dist-info/WHEEL
getproxy-0.2.3.dist-info/entry_points.txt
getproxy-0.2.3.dist-info/metadata.json
getproxy-0.2.3.dist-info/top_level.txt
