Metadata-Version: 2.0
Name: getproxy
Version: 0.2.3
Summary: get proxy
Home-page: https://github.com/fate0/getproxy
Author: fate0
Author-email: fate0@fatezero.org
License: BSD license
Keywords: getproxy
Platform: UNKNOWN
Classifier: Development Status :: 2 - Pre-Alpha
Classifier: Intended Audience :: Developers
Classifier: License :: OSI Approved :: BSD License
Classifier: Natural Language :: English
Classifier: Programming Language :: Python :: 2
Classifier: Programming Language :: Python :: 2.7
Classifier: Programming Language :: Python :: 3
Classifier: Programming Language :: Python :: 3.3
Classifier: Programming Language :: Python :: 3.4
Classifier: Programming Language :: Python :: 3.5
Requires-Dist: click (>=6.0)
Requires-Dist: geoip2 (>=2.5.0)
Requires-Dist: gevent (>=1.2.1)
Requires-Dist: requests (>=2.13.0)
Requires-Dist: retrying (>=1.3.3)
